dmipy/__init__.py
dmipy/version.py
dmipy/core/__init__.py
dmipy/core/acquisition_scheme.py
dmipy/core/constants.py
dmipy/core/fitted_modeling_framework.py
dmipy/core/gradient_conversions.py
dmipy/core/modeling_framework.py
dmipy/core/signal_model_properties.py
dmipy/custom_optimizers/__init__.py
dmipy/custom_optimizers/intra_voxel_incoherent_motion.py
dmipy/custom_optimizers/single_shell_three_tissue_csd.py
dmipy/data/__init__.py
dmipy/data/bingham_normalization_splinefit.npz
dmipy/data/saved_acquisition_schemes.py
dmipy/data/saved_data.py
dmipy/data/wu_minn_hcp_subjects.txt
dmipy/data/camino/data_camino_D1_7.txt
dmipy/data/camino/data_camino_D2_0.txt
dmipy/data/camino/data_camino_D2_3.txt
dmipy/data/camino/data_camino_dispersed_D1_7.txt
dmipy/data/camino/data_camino_dispersed_D2_0.txt
dmipy/data/camino/data_camino_dispersed_D2_3.txt
dmipy/data/camino/fractions_camino_D1_7.txt
dmipy/data/camino/fractions_camino_D2_0.txt
dmipy/data/camino/fractions_camino_D2_3.txt
dmipy/data/camino/parameters_camino_dispersed_D1_7.txt
dmipy/data/camino/parameters_camino_dispersed_D2_0.txt
dmipy/data/camino/parameters_camino_dispersed_D2_3.txt
dmipy/data/de_santis_camino/deSantis_scheme.scheme
dmipy/data/de_santis_camino/deSantis_signal.txt
dmipy/data/gradient_tables/bvals_hcp_wu_minn.txt
dmipy/data/gradient_tables/bvecs_hcp_wu_minn.txt
dmipy/data/gradient_tables/delta_Delta_hcp_wu_minn.txt
dmipy/data/gradient_tables/schemefile_hcp_wu_minn.scheme1
dmipy/data/gradient_tables/sphere_150.txt
dmipy/data/gradient_tables/sphere_with_cap.txt
dmipy/data/isbi2015_white_matter_challenge/fornix.txt
dmipy/data/isbi2015_white_matter_challenge/genu.txt
dmipy/data/isbi2015_white_matter_challenge/isbi_schemefile.txt
dmipy/data/spheres/01-shells-1.txt
dmipy/data/spheres/01-shells-10.txt
dmipy/data/spheres/01-shells-11.txt
dmipy/data/spheres/01-shells-12.txt
dmipy/data/spheres/01-shells-13.txt
dmipy/data/spheres/01-shells-14.txt
dmipy/data/spheres/01-shells-15.txt
dmipy/data/spheres/01-shells-16.txt
dmipy-1.0.5.dist-info/LICENSE
dmipy-1.0.5.dist-info/METADATA
dmipy-1.0.5.dist-info/WHEEL
dmipy-1.0.5.dist-info/top_level.txt
dmipy-1.0.5.dist-info/RECORD
